pixid/PixID.py
pixid/__init__.py
PixID-1.0.0.dist-info/LICENSE
PixID-1.0.0.dist-info/METADATA
PixID-1.0.0.dist-info/WHEEL
PixID-1.0.0.dist-info/top_level.txt
PixID-1.0.0.dist-info/RECORD
