Metadata-Version: 2.1
Name: PixID
Version: 1.0.0
Summary: Generates a unique identifier for the computer.
Home-page: https://github.com/ttwizz
Author: ttwiz_z
Author-email: moderkascriptsltd@gmail.com
Project-URL: Organization, https://github.com/ModerkaScripts
Keywords: PixID
Classifier: Programming Language :: Python :: 3.10
Classifier: License :: OSI Approved :: MIT License
Classifier: Operating System :: OS Independent
Requires-Python: >=3.8
License-File: LICENSE
